<?xml version="1.0"?>

<PropertyList>
  <awy>
    <id type="string">CRDR2</id>
    <wp1 type="string">AR</wp1>
    <wp2 type="string">BG</wp2>
  </awy>
  <awy n="1">
    <id type="string">CRDR1</id>
    <wp1 type="string">BD</wp1>
    <wp2 type="string">SW</wp2>
  </awy>
  <awy n="2">
    <id type="string">CRDR6</id>
    <wp1 type="string">DK</wp1>
    <wp2 type="string">FV</wp2>
  </awy>
  <awy n="3">
    <id type="string">CRDR5</id>
    <wp1 type="string">DR</wp1>
    <wp2 type="string">IN</wp2>
  </awy>
  <awy n="4">
    <id type="string">CRDR7</id>
    <wp1 type="string">FE</wp1>
    <wp2 type="string">QO</wp2>
  </awy>
  <awy n="5">
    <id type="string">CRDR3</id>
    <wp1 type="string">FK</wp1>
    <wp2 type="string">UM</wp2>
  </awy>
  <awy n="6">
    <id type="string">CRDR4</id>
    <wp1 type="string">IP</wp1>
    <wp2 type="string">WZ</wp2>
  </awy>
  <awy n="7">
    <id type="string">CRDR9</id>
    <wp1 type="string">ITINA</wp1>
    <wp2 type="string">MF</wp2>
  </awy>
  <awy n="8">
    <id type="string">CRDR9</id>
    <wp1 type="string">ITINA</wp1>
    <wp2 type="string">RW</wp2>
  </awy>
  <awy n="9">
    <id type="string">CRDR10</id>
    <wp1 type="string">KN</wp1>
    <wp2 type="string">NE</wp2>
  </awy>
  <awy n="10">
    <id type="string">CRDR8</id>
    <wp1 type="string">LEDNI</wp1>
    <wp2 type="string">SF</wp2>
  </awy>
  <awy n="11">
    <id type="string">CRDR2</id>
    <wp1 type="string">AR</wp1>
    <wp2 type="string">BG</wp2>
  </awy>
  <awy n="12">
    <id type="string">CRDR1</id>
    <wp1 type="string">BD</wp1>
    <wp2 type="string">SW</wp2>
  </awy>
  <awy n="13">
    <id type="string">CRDR6</id>
    <wp1 type="string">DK</wp1>
    <wp2 type="string">FV</wp2>
  </awy>
  <awy n="14">
    <id type="string">CRDR5</id>
    <wp1 type="string">DR</wp1>
    <wp2 type="string">IN</wp2>
  </awy>
  <awy n="15">
    <id type="string">CRDR7</id>
    <wp1 type="string">FE</wp1>
    <wp2 type="string">QO</wp2>
  </awy>
  <awy n="16">
    <id type="string">CRDR3</id>
    <wp1 type="string">FK</wp1>
    <wp2 type="string">UM</wp2>
  </awy>
  <awy n="17">
    <id type="string">CRDR4</id>
    <wp1 type="string">IP</wp1>
    <wp2 type="string">WZ</wp2>
  </awy>
  <awy n="18">
    <id type="string">CRDR9</id>
    <wp1 type="string">ITINA</wp1>
    <wp2 type="string">MF</wp2>
  </awy>
  <awy n="19">
    <id type="string">CRDR9</id>
    <wp1 type="string">ITINA</wp1>
    <wp2 type="string">RW</wp2>
  </awy>
  <awy n="20">
    <id type="string">CRDR10</id>
    <wp1 type="string">KN</wp1>
    <wp2 type="string">NE</wp2>
  </awy>
  <awy n="21">
    <id type="string">CRDR8</id>
    <wp1 type="string">LEDNI</wp1>
    <wp2 type="string">SF</wp2>
  </awy>
</PropertyList>
