<?xml version="1.0"?>

<PropertyList>
  <awy>
    <id type="string">L26</id>
    <wp1 type="string">ADELU</wp1>
    <wp2 type="string">MAMUL</wp2>
  </awy>
  <awy n="1">
    <id type="string">L29</id>
    <wp1 type="string">ALUKA</wp1>
    <wp2 type="string">TADAK</wp2>
  </awy>
  <awy n="2">
    <id type="string">L223</id>
    <wp1 type="string">ANVIX</wp1>
    <wp2 type="string">NALTA</wp2>
  </awy>
  <awy n="3">
    <id type="string">L223</id>
    <wp1 type="string">ANVIX</wp1>
    <wp2 type="string">TARDI</wp2>
  </awy>
  <awy n="4">
    <id type="string">L28</id>
    <wp1 type="string">ASNIP</wp1>
    <wp2 type="string">MCT</wp2>
  </awy>
  <awy n="5">
    <id type="string">L28</id>
    <wp1 type="string">ASNIP</wp1>
    <wp2 type="string">PENIL</wp2>
  </awy>
  <awy n="6">
    <id type="string">L212</id>
    <wp1 type="string">BIBAS</wp1>
    <wp2 type="string">KODIX</wp2>
  </awy>
  <awy n="7">
    <id type="string">L212</id>
    <wp1 type="string">BIBAS</wp1>
    <wp2 type="string">POBIN</wp2>
  </awy>
  <awy n="8">
    <id type="string">L23</id>
    <wp1 type="string">BINKA</wp1>
    <wp2 type="string">TOMKO</wp2>
  </awy>
  <awy n="9">
    <id type="string">L26</id>
    <wp1 type="string">DOPEK</wp1>
    <wp2 type="string">MAMUL</wp2>
  </awy>
  <awy n="10">
    <id type="string">L26</id>
    <wp1 type="string">DOPEK</wp1>
    <wp2 type="string">TNT63</wp2>
  </awy>
  <awy n="11">
    <id type="string">L23</id>
    <wp1 type="string">GORAT</wp1>
    <wp2 type="string">OGARA</wp2>
  </awy>
  <awy n="12">
    <id type="string">L23</id>
    <wp1 type="string">GRU</wp1>
    <wp2 type="string">OGRUD</wp2>
  </awy>
  <awy n="13">
    <id type="string">L29</id>
    <wp1 type="string">GRU</wp1>
    <wp2 type="string">OLKIN</wp2>
  </awy>
  <awy n="14">
    <id type="string">L29</id>
    <wp1 type="string">GRU</wp1>
    <wp2 type="string">TADAK</wp2>
  </awy>
  <awy n="15">
    <id type="string">L2</id>
    <wp1 type="string">KOLEX</wp1>
    <wp2 type="string">RALAK</wp2>
  </awy>
  <awy n="16">
    <id type="string">L29</id>
    <wp1 type="string">LAVAR</wp1>
    <wp2 type="string">SUBUS</wp2>
  </awy>
  <awy n="17">
    <id type="string">L23</id>
    <wp1 type="string">LOVIK</wp1>
    <wp2 type="string">OGARA</wp2>
  </awy>
  <awy n="18">
    <id type="string">L28</id>
    <wp1 type="string">MCT</wp1>
    <wp2 type="string">RODOL</wp2>
  </awy>
  <awy n="19">
    <id type="string">L223</id>
    <wp1 type="string">MUTVI</wp1>
    <wp2 type="string">RAGOL</wp2>
  </awy>
  <awy n="20">
    <id type="string">L223</id>
    <wp1 type="string">MUTVI</wp1>
    <wp2 type="string">SHJ59</wp2>
  </awy>
  <awy n="21">
    <id type="string">L223</id>
    <wp1 type="string">NALTA</wp1>
    <wp2 type="string">RAGOL</wp2>
  </awy>
  <awy n="22">
    <id type="string">L23</id>
    <wp1 type="string">OGRUD</wp1>
    <wp2 type="string">TOMKO</wp2>
  </awy>
  <awy n="23">
    <id type="string">L29</id>
    <wp1 type="string">OLKIN</wp1>
    <wp2 type="string">SUW</wp2>
  </awy>
  <awy n="24">
    <id type="string">L212</id>
    <wp1 type="string">ONPAD</wp1>
    <wp2 type="string">POBIN</wp2>
  </awy>
  <awy n="25">
    <id type="string">L26</id>
    <wp1 type="string">OTBED</wp1>
    <wp2 type="string">TNT63</wp2>
  </awy>
  <awy n="26">
    <id type="string">L200</id>
    <wp1 type="string">PASIP</wp1>
    <wp2 type="string">RAPLU</wp2>
  </awy>
  <awy n="27">
    <id type="string">L28</id>
    <wp1 type="string">RODOL</wp1>
    <wp2 type="string">TNT</wp2>
  </awy>
  <awy n="28">
    <id type="string">L223</id>
    <wp1 type="string">SHJ59</wp1>
    <wp2 type="string">SIR</wp2>
  </awy>
  <awy n="29">
    <id type="string">L29</id>
    <wp1 type="string">SUBUS</wp1>
    <wp2 type="string">VABER</wp2>
  </awy>
  <awy n="30">
    <id type="string">L29</id>
    <wp1 type="string">SUW</wp1>
    <wp2 type="string">VABER</wp2>
  </awy>
  <awy n="31">
    <id type="string">L212</id>
    <wp1 type="string">UHG</wp1>
    <wp2 type="string">URLAM</wp2>
  </awy>
  <awy n="32">
    <id type="string">L223</id>
    <wp1 type="string">ANVIX</wp1>
    <wp2 type="string">NALTA</wp2>
  </awy>
  <awy n="33">
    <id type="string">L223</id>
    <wp1 type="string">ANVIX</wp1>
    <wp2 type="string">TARDI</wp2>
  </awy>
  <awy n="34">
    <id type="string">L223</id>
    <wp1 type="string">LAKLU</wp1>
    <wp2 type="string">TARDI</wp2>
  </awy>
  <awy n="35">
    <id type="string">L223</id>
    <wp1 type="string">MUTVI</wp1>
    <wp2 type="string">RAGOL</wp2>
  </awy>
  <awy n="36">
    <id type="string">L223</id>
    <wp1 type="string">MUTVI</wp1>
    <wp2 type="string">SHJ59</wp2>
  </awy>
  <awy n="37">
    <id type="string">L223</id>
    <wp1 type="string">NALTA</wp1>
    <wp2 type="string">RAGOL</wp2>
  </awy>
  <awy n="38">
    <id type="string">L200</id>
    <wp1 type="string">PASIP</wp1>
    <wp2 type="string">RAPLU</wp2>
  </awy>
  <awy n="39">
    <id type="string">L223</id>
    <wp1 type="string">SHJ59</wp1>
    <wp2 type="string">SIR</wp2>
  </awy>
</PropertyList>
