<?xml version="1.0"?>

<PropertyList>
  <awy>
    <id type="string">P155</id>
    <wp1 type="string">ABEDA</wp1>
    <wp2 type="string">BANEM</wp2>
  </awy>
  <awy n="1">
    <id type="string">P121</id>
    <wp1 type="string">ADAKA</wp1>
    <wp2 type="string">TIGTA</wp2>
  </awy>
  <awy n="2">
    <id type="string">P121</id>
    <wp1 type="string">ADAKA</wp1>
    <wp2 type="string">TIPEN</wp2>
  </awy>
  <awy n="3">
    <id type="string">P152</id>
    <wp1 type="string">ADEDI</wp1>
    <wp2 type="string">BAPOR</wp2>
  </awy>
  <awy n="4">
    <id type="string">P152</id>
    <wp1 type="string">ADEDI</wp1>
    <wp2 type="string">PODUX</wp2>
  </awy>
  <awy n="5">
    <id type="string">P159</id>
    <wp1 type="string">ADERI</wp1>
    <wp2 type="string">SOMOV</wp2>
  </awy>
  <awy n="6">
    <id type="string">P159</id>
    <wp1 type="string">ADERI</wp1>
    <wp2 type="string">VALPA</wp2>
  </awy>
  <awy n="7">
    <id type="string">P18</id>
    <wp1 type="string">ADN</wp1>
    <wp2 type="string">ADN24</wp2>
  </awy>
  <awy n="8">
    <id type="string">P18</id>
    <wp1 type="string">ADN24</wp1>
    <wp2 type="string">ADN30</wp2>
  </awy>
  <awy n="9">
    <id type="string">P18</id>
    <wp1 type="string">ADN30</wp1>
    <wp2 type="string">ADN40</wp2>
  </awy>
  <awy n="10">
    <id type="string">P18</id>
    <wp1 type="string">ADN40</wp1>
    <wp2 type="string">BALID</wp2>
  </awy>
  <awy n="11">
    <id type="string">P131</id>
    <wp1 type="string">ADOSA</wp1>
    <wp2 type="string">GIGGI</wp2>
  </awy>
  <awy n="12">
    <id type="string">P10</id>
    <wp1 type="string">ADULA</wp1>
    <wp2 type="string">CE</wp2>
  </awy>
  <awy n="13">
    <id type="string">P10</id>
    <wp1 type="string">ADULA</wp1>
    <wp2 type="string">VIBOP</wp2>
  </awy>
  <awy n="14">
    <id type="string">P128</id>
    <wp1 type="string">AGZ</wp1>
    <wp2 type="string">LUNOV</wp2>
  </awy>
  <awy n="15">
    <id type="string">P127</id>
    <wp1 type="string">AKIRA</wp1>
    <wp2 type="string">GODOR</wp2>
  </awy>
  <awy n="16">
    <id type="string">P127</id>
    <wp1 type="string">AKIRA</wp1>
    <wp2 type="string">UDEKA</wp2>
  </awy>
  <awy n="17">
    <id type="string">P18</id>
    <wp1 type="string">ALASO</wp1>
    <wp2 type="string">MADAD</wp2>
  </awy>
  <awy n="18">
    <id type="string">P18</id>
    <wp1 type="string">ALASO</wp1>
    <wp2 type="string">NEW05</wp2>
  </awy>
  <awy n="19">
    <id type="string">P151</id>
    <wp1 type="string">ALIVO</wp1>
    <wp2 type="string">ELDUM</wp2>
  </awy>
  <awy n="20">
    <id type="string">P151</id>
    <wp1 type="string">ALIVO</wp1>
    <wp2 type="string">RJK</wp2>
  </awy>
  <awy n="21">
    <id type="string">P150</id>
    <wp1 type="string">AMUTO</wp1>
    <wp2 type="string">DODEK</wp2>
  </awy>
  <awy n="22">
    <id type="string">P150</id>
    <wp1 type="string">AMUTO</wp1>
    <wp2 type="string">OBOKU</wp2>
  </awy>
  <awy n="23">
    <id type="string">P146</id>
    <wp1 type="string">ARI</wp1>
    <wp2 type="string">YAVUZ</wp2>
  </awy>
  <awy n="24">
    <id type="string">P161</id>
    <wp1 type="string">ARNEB</wp1>
    <wp2 type="string">KIRAS</wp2>
  </awy>
  <awy n="25">
    <id type="string">P161</id>
    <wp1 type="string">ARNEB</wp1>
    <wp2 type="string">NAVED</wp2>
  </awy>
  <awy n="26">
    <id type="string">P125</id>
    <wp1 type="string">ARNOS</wp1>
    <wp2 type="string">TIBRO</wp2>
  </awy>
  <awy n="27">
    <id type="string">P125</id>
    <wp1 type="string">ARNOS</wp1>
    <wp2 type="string">VIW</wp2>
  </awy>
  <awy n="28">
    <id type="string">P171</id>
    <wp1 type="string">ARSAM</wp1>
    <wp2 type="string">GONOS</wp2>
  </awy>
  <awy n="29">
    <id type="string">P171</id>
    <wp1 type="string">ARSAM</wp1>
    <wp2 type="string">INTOR</wp2>
  </awy>
  <awy n="30">
    <id type="string">P121</id>
    <wp1 type="string">BADAS</wp1>
    <wp2 type="string">KZO</wp2>
  </awy>
  <awy n="31">
    <id type="string">P121</id>
    <wp1 type="string">BADAS</wp1>
    <wp2 type="string">TIPEN</wp2>
  </awy>
  <awy n="32">
    <id type="string">P152</id>
    <wp1 type="string">BADRU</wp1>
    <wp2 type="string">BAPOR</wp2>
  </awy>
  <awy n="33">
    <id type="string">P152</id>
    <wp1 type="string">BADRU</wp1>
    <wp2 type="string">NENEM</wp2>
  </awy>
  <awy n="34">
    <id type="string">P11</id>
    <wp1 type="string">BAKSO</wp1>
    <wp2 type="string">PUL</wp2>
  </awy>
  <awy n="35">
    <id type="string">P11</id>
    <wp1 type="string">BAKSO</wp1>
    <wp2 type="string">ROTAR</wp2>
  </awy>
  <awy n="36">
    <id type="string">P126</id>
    <wp1 type="string">BALGO</wp1>
    <wp2 type="string">NT</wp2>
  </awy>
  <awy n="37">
    <id type="string">P18</id>
    <wp1 type="string">BALID</wp1>
    <wp2 type="string">NEXUS</wp2>
  </awy>
  <awy n="38">
    <id type="string">P155</id>
    <wp1 type="string">BANEM</wp1>
    <wp2 type="string">UMBAG</wp2>
  </awy>
  <awy n="39">
    <id type="string">P166</id>
    <wp1 type="string">BANTO</wp1>
    <wp2 type="string">CFD13</wp2>
  </awy>
  <awy n="40">
    <id type="string">P155</id>
    <wp1 type="string">BANTO</wp1>
    <wp2 type="string">EBOTO</wp2>
  </awy>
  <awy n="41">
    <id type="string">P155</id>
    <wp1 type="string">BANTO</wp1>
    <wp2 type="string">SIVDA</wp2>
  </awy>
  <awy n="42">
    <id type="string">P1</id>
    <wp1 type="string">BINBO</wp1>
    <wp2 type="string">GODOS</wp2>
  </awy>
  <awy n="43">
    <id type="string">P1</id>
    <wp1 type="string">BINBO</wp1>
    <wp2 type="string">ROKAN</wp2>
  </awy>
  <awy n="44">
    <id type="string">P127</id>
    <wp1 type="string">BLH</wp1>
    <wp2 type="string">LASDO</wp2>
  </awy>
  <awy n="45">
    <id type="string">P195</id>
    <wp1 type="string">BOL</wp1>
    <wp2 type="string">GILIO</wp2>
  </awy>
  <awy n="46">
    <id type="string">P142</id>
    <wp1 type="string">BOL</wp1>
    <wp2 type="string">MEDAL</wp2>
  </awy>
  <awy n="47">
    <id type="string">P144</id>
    <wp1 type="string">BUSOM</wp1>
    <wp2 type="string">GOLUM</wp2>
  </awy>
  <awy n="48">
    <id type="string">P161</id>
    <wp1 type="string">CAR</wp1>
    <wp2 type="string">NOLSI</wp2>
  </awy>
  <awy n="49">
    <id type="string">P166</id>
    <wp1 type="string">CFD13</wp1>
    <wp2 type="string">OLNEY</wp2>
  </awy>
  <awy n="50">
    <id type="string">P155</id>
    <wp1 type="string">CFD33</wp1>
    <wp2 type="string">SIVDA</wp2>
  </awy>
  <awy n="51">
    <id type="string">P155</id>
    <wp1 type="string">CFD33</wp1>
    <wp2 type="string">UMBAG</wp2>
  </awy>
  <awy n="52">
    <id type="string">P133</id>
    <wp1 type="string">CHN</wp1>
    <wp2 type="string">TURSA</wp2>
  </awy>
  <awy n="53">
    <id type="string">P133</id>
    <wp1 type="string">CHN</wp1>
    <wp2 type="string">UNIRA</wp2>
  </awy>
  <awy n="54">
    <id type="string">P11</id>
    <wp1 type="string">CRE</wp1>
    <wp2 type="string">OBALA</wp2>
  </awy>
  <awy n="55">
    <id type="string">P11</id>
    <wp1 type="string">CRE</wp1>
    <wp2 type="string">PUL</wp2>
  </awy>
  <awy n="56">
    <id type="string">P151</id>
    <wp1 type="string">CRE</wp1>
    <wp2 type="string">RJK</wp2>
  </awy>
  <awy n="57">
    <id type="string">P150</id>
    <wp1 type="string">CZE</wp1>
    <wp2 type="string">DOREM</wp2>
  </awy>
  <awy n="58">
    <id type="string">P11</id>
    <wp1 type="string">DABAR</wp1>
    <wp2 type="string">OBALA</wp2>
  </awy>
  <awy n="59">
    <id type="string">P11</id>
    <wp1 type="string">DABAR</wp1>
    <wp2 type="string">RASTU</wp2>
  </awy>
  <awy n="60">
    <id type="string">P15</id>
    <wp1 type="string">DANKO</wp1>
    <wp2 type="string">VAXIT</wp2>
  </awy>
  <awy n="61">
    <id type="string">P11</id>
    <wp1 type="string">DER</wp1>
    <wp2 type="string">KOMAR</wp2>
  </awy>
  <awy n="62">
    <id type="string">P11</id>
    <wp1 type="string">DER</wp1>
    <wp2 type="string">VIBOP</wp2>
  </awy>
  <awy n="63">
    <id type="string">P127</id>
    <wp1 type="string">DOBAR</wp1>
    <wp2 type="string">SKJ</wp2>
  </awy>
  <awy n="64">
    <id type="string">P127</id>
    <wp1 type="string">DOBAR</wp1>
    <wp2 type="string">UNDER</wp2>
  </awy>
  <awy n="65">
    <id type="string">P151</id>
    <wp1 type="string">DOL</wp1>
    <wp2 type="string">ELDUM</wp2>
  </awy>
  <awy n="66">
    <id type="string">P150</id>
    <wp1 type="string">DOREM</wp1>
    <wp2 type="string">OBOKU</wp2>
  </awy>
  <awy n="67">
    <id type="string">P155</id>
    <wp1 type="string">EBOTO</wp1>
    <wp2 type="string">HON</wp2>
  </awy>
  <awy n="68">
    <id type="string">P159</id>
    <wp1 type="string">FLR</wp1>
    <wp2 type="string">VALPA</wp2>
  </awy>
  <awy n="69">
    <id type="string">P18</id>
    <wp1 type="string">GASKO</wp1>
    <wp2 type="string">POL22</wp2>
  </awy>
  <awy n="70">
    <id type="string">P18</id>
    <wp1 type="string">GASKO</wp1>
    <wp2 type="string">UVAVU</wp2>
  </awy>
  <awy n="71">
    <id type="string">P131</id>
    <wp1 type="string">GIGGI</wp1>
    <wp2 type="string">RESIA</wp2>
  </awy>
  <awy n="72">
    <id type="string">P160</id>
    <wp1 type="string">GILET</wp1>
    <wp2 type="string">KISTO</wp2>
  </awy>
  <awy n="73">
    <id type="string">P127</id>
    <wp1 type="string">GODOR</wp1>
    <wp2 type="string">KONAT</wp2>
  </awy>
  <awy n="74">
    <id type="string">P1</id>
    <wp1 type="string">GODOS</wp1>
    <wp2 type="string">SUPUR</wp2>
  </awy>
  <awy n="75">
    <id type="string">P127</id>
    <wp1 type="string">GODVA</wp1>
    <wp2 type="string">LASDO</wp2>
  </awy>
  <awy n="76">
    <id type="string">P127</id>
    <wp1 type="string">GODVA</wp1>
    <wp2 type="string">UDEKA</wp2>
  </awy>
  <awy n="77">
    <id type="string">P127</id>
    <wp1 type="string">GOKEL</wp1>
    <wp2 type="string">UNDER</wp2>
  </awy>
  <awy n="78">
    <id type="string">P144</id>
    <wp1 type="string">GOLUM</wp1>
    <wp2 type="string">SOPTO</wp2>
  </awy>
  <awy n="79">
    <id type="string">P133</id>
    <wp1 type="string">IAS</wp1>
    <wp2 type="string">UNIRA</wp2>
  </awy>
  <awy n="80">
    <id type="string">P128</id>
    <wp1 type="string">JBA</wp1>
    <wp2 type="string">KIRAS</wp2>
  </awy>
  <awy n="81">
    <id type="string">P128</id>
    <wp1 type="string">JBA</wp1>
    <wp2 type="string">TANLI</wp2>
  </awy>
  <awy n="82">
    <id type="string">P10</id>
    <wp1 type="string">KEB</wp1>
    <wp2 type="string">VIBOP</wp2>
  </awy>
  <awy n="83">
    <id type="string">P192</id>
    <wp1 type="string">KEROP</wp1>
    <wp2 type="string">TISAK</wp2>
  </awy>
  <awy n="84">
    <id type="string">P160</id>
    <wp1 type="string">KISTO</wp1>
    <wp2 type="string">PODOX</wp2>
  </awy>
  <awy n="85">
    <id type="string">P11</id>
    <wp1 type="string">KOMAR</wp1>
    <wp2 type="string">RASTU</wp2>
  </awy>
  <awy n="86">
    <id type="string">P127</id>
    <wp1 type="string">KONAT</wp1>
    <wp2 type="string">UAAT</wp2>
  </awy>
  <awy n="87">
    <id type="string">P122</id>
    <wp1 type="string">KURAB</wp1>
    <wp2 type="string">LATNU</wp2>
  </awy>
  <awy n="88">
    <id type="string">P122</id>
    <wp1 type="string">KURAB</wp1>
    <wp2 type="string">UTNN</wp2>
  </awy>
  <awy n="89">
    <id type="string">P125</id>
    <wp1 type="string">LAGUN</wp1>
    <wp2 type="string">RONNB</wp2>
  </awy>
  <awy n="90">
    <id type="string">P125</id>
    <wp1 type="string">LAGUN</wp1>
    <wp2 type="string">ROSKA</wp2>
  </awy>
  <awy n="91">
    <id type="string">P122</id>
    <wp1 type="string">LATNU</wp1>
    <wp2 type="string">NKZ</wp2>
  </awy>
  <awy n="92">
    <id type="string">P161</id>
    <wp1 type="string">LOBNA</wp1>
    <wp2 type="string">NAVED</wp2>
  </awy>
  <awy n="93">
    <id type="string">P161</id>
    <wp1 type="string">LOBNA</wp1>
    <wp2 type="string">TUC</wp2>
  </awy>
  <awy n="94">
    <id type="string">P128</id>
    <wp1 type="string">LUNOV</wp1>
    <wp2 type="string">ROKOD</wp2>
  </awy>
  <awy n="95">
    <id type="string">P125</id>
    <wp1 type="string">LUPIN</wp1>
    <wp2 type="string">RONNB</wp2>
  </awy>
  <awy n="96">
    <id type="string">P125</id>
    <wp1 type="string">LUPIN</wp1>
    <wp2 type="string">TIBRO</wp2>
  </awy>
  <awy n="97">
    <id type="string">P18</id>
    <wp1 type="string">MADAD</wp1>
    <wp2 type="string">NEXUS</wp2>
  </awy>
  <awy n="98">
    <id type="string">P160</id>
    <wp1 type="string">MEDAL</wp1>
    <wp2 type="string">OST</wp2>
  </awy>
  <awy n="99">
    <id type="string">P160</id>
    <wp1 type="string">MEDAL</wp1>
    <wp2 type="string">ROTIR</wp2>
  </awy>
  <awy n="100">
    <id type="string">P1</id>
    <wp1 type="string">MONIL</wp1>
    <wp2 type="string">SUPUR</wp2>
  </awy>
  <awy n="101">
    <id type="string">P192</id>
    <wp1 type="string">NEPOS</wp1>
    <wp2 type="string">TISAK</wp2>
  </awy>
  <awy n="102">
    <id type="string">P18</id>
    <wp1 type="string">NEW</wp1>
    <wp2 type="string">NEW05</wp2>
  </awy>
  <awy n="103">
    <id type="string">P18</id>
    <wp1 type="string">NEW</wp1>
    <wp2 type="string">NEW20</wp2>
  </awy>
  <awy n="104">
    <id type="string">P18</id>
    <wp1 type="string">NEW20</wp1>
    <wp2 type="string">TILNI</wp2>
  </awy>
  <awy n="105">
    <id type="string">P160</id>
    <wp1 type="string">PODOX</wp1>
    <wp2 type="string">ROTIR</wp2>
  </awy>
  <awy n="106">
    <id type="string">P152</id>
    <wp1 type="string">PODUX</wp1>
    <wp2 type="string">PPN</wp2>
  </awy>
  <awy n="107">
    <id type="string">P17</id>
    <wp1 type="string">POL</wp1>
    <wp2 type="string">POL21</wp2>
  </awy>
  <awy n="108">
    <id type="string">P18</id>
    <wp1 type="string">POL</wp1>
    <wp2 type="string">POL22</wp2>
  </awy>
  <awy n="109">
    <id type="string">P17</id>
    <wp1 type="string">POL21</wp1>
    <wp2 type="string">RIPNO</wp2>
  </awy>
  <awy n="110">
    <id type="string">P1</id>
    <wp1 type="string">ROKAN</wp1>
    <wp2 type="string">TINDI</wp2>
  </awy>
  <awy n="111">
    <id type="string">P128</id>
    <wp1 type="string">ROKOD</wp1>
    <wp2 type="string">UASS</wp2>
  </awy>
  <awy n="112">
    <id type="string">P137</id>
    <wp1 type="string">SONDO</wp1>
    <wp2 type="string">UMBAG</wp2>
  </awy>
  <awy n="113">
    <id type="string">P146</id>
    <wp1 type="string">TBN</wp1>
    <wp2 type="string">YAVUZ</wp2>
  </awy>
  <awy n="114">
    <id type="string">P121</id>
    <wp1 type="string">TIGTA</wp1>
    <wp2 type="string">UTNN</wp2>
  </awy>
  <awy n="115">
    <id type="string">P18</id>
    <wp1 type="string">TILNI</wp1>
    <wp2 type="string">UVAVU</wp2>
  </awy>
  <awy n="116">
    <id type="string">P11</id>
    <wp1 type="string">TUVAR</wp1>
    <wp2 type="string">VIBOP</wp2>
  </awy>
  <awy n="117">
    <id type="string">P121</id>
    <wp1 type="string">ADAKA</wp1>
    <wp2 type="string">TIGTA</wp2>
  </awy>
  <awy n="118">
    <id type="string">P121</id>
    <wp1 type="string">ADAKA</wp1>
    <wp2 type="string">TIPEN</wp2>
  </awy>
  <awy n="119">
    <id type="string">P128</id>
    <wp1 type="string">AGZ</wp1>
    <wp2 type="string">LUNOV</wp2>
  </awy>
  <awy n="120">
    <id type="string">P127</id>
    <wp1 type="string">AKIRA</wp1>
    <wp2 type="string">GODOR</wp2>
  </awy>
  <awy n="121">
    <id type="string">P127</id>
    <wp1 type="string">AKIRA</wp1>
    <wp2 type="string">UDEKA</wp2>
  </awy>
  <awy n="122">
    <id type="string">P121</id>
    <wp1 type="string">BADAS</wp1>
    <wp2 type="string">KZO</wp2>
  </awy>
  <awy n="123">
    <id type="string">P121</id>
    <wp1 type="string">BADAS</wp1>
    <wp2 type="string">TIPEN</wp2>
  </awy>
  <awy n="124">
    <id type="string">P126</id>
    <wp1 type="string">BALGO</wp1>
    <wp2 type="string">NT</wp2>
  </awy>
  <awy n="125">
    <id type="string">P127</id>
    <wp1 type="string">BLH</wp1>
    <wp2 type="string">LASDO</wp2>
  </awy>
  <awy n="126">
    <id type="string">P127</id>
    <wp1 type="string">GODOR</wp1>
    <wp2 type="string">KONAT</wp2>
  </awy>
  <awy n="127">
    <id type="string">P127</id>
    <wp1 type="string">GODVA</wp1>
    <wp2 type="string">LASDO</wp2>
  </awy>
  <awy n="128">
    <id type="string">P127</id>
    <wp1 type="string">GODVA</wp1>
    <wp2 type="string">UDEKA</wp2>
  </awy>
  <awy n="129">
    <id type="string">P127</id>
    <wp1 type="string">KONAT</wp1>
    <wp2 type="string">UAAT</wp2>
  </awy>
  <awy n="130">
    <id type="string">P122</id>
    <wp1 type="string">KURAB</wp1>
    <wp2 type="string">LATNU</wp2>
  </awy>
  <awy n="131">
    <id type="string">P122</id>
    <wp1 type="string">KURAB</wp1>
    <wp2 type="string">UTNN</wp2>
  </awy>
  <awy n="132">
    <id type="string">P122</id>
    <wp1 type="string">LATNU</wp1>
    <wp2 type="string">NKZ</wp2>
  </awy>
  <awy n="133">
    <id type="string">P128</id>
    <wp1 type="string">LUNOV</wp1>
    <wp2 type="string">ROKOD</wp2>
  </awy>
  <awy n="134">
    <id type="string">P128</id>
    <wp1 type="string">ROKOD</wp1>
    <wp2 type="string">UASS</wp2>
  </awy>
  <awy n="135">
    <id type="string">P121</id>
    <wp1 type="string">TIGTA</wp1>
    <wp2 type="string">UTNN</wp2>
  </awy>
</PropertyList>
